tessif_pypsa_0_19_3/__init__.py
tessif_pypsa_0_19_3/optimize.py
tessif_pypsa_0_19_3/post_process.py
tessif_pypsa_0_19_3/transform.py
tessif_pypsa_0_19_3-0.1.1.dist-info/LICENSE
tessif_pypsa_0_19_3-0.1.1.dist-info/WHEEL
tessif_pypsa_0_19_3-0.1.1.dist-info/METADATA
tessif_pypsa_0_19_3-0.1.1.dist-info/RECORD
