Metadata-Version: 2.1
Name: tessif-pypsa-0-19-3
Version: 0.1.1
Summary: Tessif-Plugin for providing pypsa version 0.19.3 support.
Home-page: https://github.com/tZ3ma/tessif_pypsa_0_19_3
License: MIT
Keywords: Tessif,Tessif-PyPSA,ESSMOS,optimization,energy supply system modelling
Author: Mathias Ammon
Author-email: tz3ma.coding@use.startmail.com
Requires-Python: >=3.8,<4.0
Classifier: License :: OSI Approved :: MIT License
Classifier: Programming Language :: Python :: 3
Classifier: Programming Language :: Python :: 3.8
Classifier: Programming Language :: Python :: 3.9
Classifier: Programming Language :: Python :: 3.10
Classifier: Programming Language :: Python :: 3.11
Requires-Dist: pyomo (<6.0.0)
Requires-Dist: pypsa (==0.19.3)
Requires-Dist: tessif (>=0.0.24)
Project-URL: Repository, https://github.com/tZ3ma/tessif_pypsa_0_19_3
